complassist/__init__.py
complassist/_clearlydefined.py
complassist/_flict.py
complassist/_helpers.py
complassist/_licensing.py
complassist/_logging.py
complassist/_sbom_enrich.py
complassist/_sbom_generate.py
complassist/_sbom_parse.py
complassist/main.py
compliance_assistant-1.1.3.dist-info/METADATA
compliance_assistant-1.1.3.dist-info/WHEEL
compliance_assistant-1.1.3.dist-info/entry_points.txt
compliance_assistant-1.1.3.dist-info/licenses/LICENSE.txt
compliance_assistant-1.1.3.dist-info/licenses/LICENSES/Apache-2.0.txt
compliance_assistant-1.1.3.dist-info/licenses/LICENSES/CC-BY-4.0.txt
compliance_assistant-1.1.3.dist-info/RECORD
