Metadata-Version: 2.4
Name: compliance-assistant
Version: 1.1.3
Summary: Toolset that helps with creating and interacting with SBOMs, enriching with licensing and copyright information, and checking for Open Source license compliance
License: Apache-2.0
License-File: LICENSE.txt
License-File: LICENSES/Apache-2.0.txt
License-File: LICENSES/CC-BY-4.0.txt
Keywords: sbom,compliance,clearlydefined,cyclonedx,spdx,license,copyright,flict,compatibility
Author: Max Mehl
Author-email: max.mehl@deutschebahn.com
Requires-Python: >=3.10,<4.0
Classifier: Development Status :: 5 - Production/Stable
Classifier: Environment :: Console
Classifier: License :: OSI Approved :: Apache Software License
Classifier: Programming Language :: Python :: 3
Classifier: Programming Language :: Python :: 3.10
Classifier: Programming Language :: Python :: 3.11
Classifier: Programming Language :: Python :: 3.12
Classifier: Programming Language :: Python :: 3.13
Classifier: Programming Language :: Python :: 3.14
Classifier: Topic :: Software Development
Requires-Dist: docker (>=7.1.0,<8.0.0)
Requires-Dist: flict (>=1.3.0,<2.0.0)
Requires-Dist: license-expression (>=30.4.4,<31.0.0)
Requires-Dist: purl-tools (>=0.2.3,<0.3.0)
Requires-Dist: requests (>=2.32.5,<3.0.0)
Project-URL: Repository, https://github.com/OpenRailAssociation/compliance-assistant
